async_gpib/__init__.py
async_gpib/_version.py
async_gpib/async_gpib.py
async_gpib-2.1.4.dist-info/licenses/LICENSE
async_gpib-2.1.4.dist-info/METADATA
async_gpib-2.1.4.dist-info/WHEEL
async_gpib-2.1.4.dist-info/top_level.txt
async_gpib-2.1.4.dist-info/RECORD
